bdfan/__init__.py
bdfan/bdfan_with_hearts.json
bdfan/crawl-bdfan.py
bdfan-2025.8.23.post1.dist-info/licenses/LICENSE
bdfan-2025.8.23.post1.dist-info/METADATA
bdfan-2025.8.23.post1.dist-info/WHEEL
bdfan-2025.8.23.post1.dist-info/top_level.txt
bdfan-2025.8.23.post1.dist-info/RECORD
