Metadata-Version: 2.4
Name: bdfan
Version: 2025.8.23.post1
Summary: Anime birthday dataset from https://bd.fan-web.jp
Requires-Python: >=3.9
License-File: LICENSE
Dynamic: license-file
